helpers/__init__.py
helpers/functions.py
module/__init__.py
module/github.py
GitDeets-0.0.2.dist-info/LICENCE.txt
GitDeets-0.0.2.dist-info/METADATA
GitDeets-0.0.2.dist-info/WHEEL
GitDeets-0.0.2.dist-info/top_level.txt
GitDeets-0.0.2.dist-info/RECORD
