Metadata-Version: 2.1
Name: GitDeets
Version: 0.0.2
Summary: A github data scrapper package
Home-page: 
Author: Nikhil Raj
Author-email: nikhil25803@gmail.com
License: MIT
Keywords: scrapper
Classifier: Development Status :: 5 - Production/Stable
Classifier: Intended Audience :: Education
Classifier: Operating System :: OS Independent
Classifier: License :: OSI Approved :: MIT License
Classifier: Programming Language :: Python :: 3
License-File: LICENCE.txt
Requires-Dist: bs4
Requires-Dist: requests
